nonces/__init__.py
nonces/nonces.py
nonces-1.0.3.dist-info/LICENSE
nonces-1.0.3.dist-info/METADATA
nonces-1.0.3.dist-info/WHEEL
nonces-1.0.3.dist-info/top_level.txt
nonces-1.0.3.dist-info/RECORD
