Metadata-Version: 2.1
Name: nonces
Version: 1.0.3
Summary: Nonces generator for cryptographic purposes
Home-page: https://github.com/gonatienza/nonces/
Author: Gonzalo Atienza Rela
Author-email: gonatienza@gmail.com
License: Apache License 2.0
Requires-Python: >=3.8
License-File: LICENSE
